vgn/__init__.py
vgn/converter.py
vgn/data_classes.py
vgn/exceptions.py
vgn/functions.py
vgn/test_api.py
vgn-2.0.0.dist-info/LICENSE
vgn-2.0.0.dist-info/METADATA
vgn-2.0.0.dist-info/WHEEL
vgn-2.0.0.dist-info/top_level.txt
vgn-2.0.0.dist-info/RECORD
