Metadata-Version: 2.1
Name: vgn
Version: 2.0.0
Summary: VGN async API for python 3
Home-page: https://github.com/becheran/vgn
Author: Armin Becher
Author-email: becherarmin@gmail.com
License: UNKNOWN
Platform: UNKNOWN
Classifier: Intended Audience :: Developers
Classifier: Programming Language :: Python :: 3.7
Classifier: Programming Language :: Python :: 3.8
Classifier: License :: OSI Approved :: MIT License
Classifier: Operating System :: OS Independent
Requires-Python: >=3.7
Requires-Dist: python-dateutil
Requires-Dist: aiohttp (<4,>=3.6.2)
